decuen/__init__.py
decuen/actors/__init__.py
decuen/actors/_actor.py
decuen/agents/__init__.py
decuen/agents/_agent.py
decuen/agents/q.py
decuen/critics/__init__.py
decuen/critics/_critic.py
decuen/critics/_q.py
decuen/critics/dqn.py
decuen/critics/qtable.py
decuen/dists/__init__.py
decuen/dists/_distribution.py
decuen/memories/__init__.py
decuen/memories/_memory.py
decuen/memories/short_term.py
decuen/memories/uniform.py
decuen/policies/__init__.py
decuen/policies/_policy.py
decuen/strategies/__init__.py
decuen/strategies/_strategy.py
decuen/strategies/epsilon.py
decuen/strategies/greedy.py
decuen/strategies/rand.py
decuen/utils/__init__.py
decuen/utils/checks.py
decuen/utils/context.py
decuen/utils/function_property.py
decuen-0.0.5.dist-info/LICENSE
decuen-0.0.5.dist-info/METADATA
decuen-0.0.5.dist-info/WHEEL
decuen-0.0.5.dist-info/top_level.txt
decuen-0.0.5.dist-info/RECORD
