Metadata-Version: 2.1
Name: decuen
Version: 0.0.5
Summary: Reinforcement learning framework built in modern Python for experimentation, ease-of-use, modularity, and extensibility.
Home-page: https://github.com/ziyadedher/decuen
Author: Ziyad Edher
Author-email: ziyad.edher@gmail.com
License: MIT
Download-URL: https://github.com/ziyadedher/decuen/tags
Platform: any
Classifier: Development Status :: 1 - Planning
Classifier: Intended Audience :: Developers
Classifier: Intended Audience :: Science/Research
Classifier: Natural Language :: English
Classifier: Operating System :: OS Independent
Classifier: Programming Language :: Python :: 3.7
Classifier: Programming Language :: Python :: 3 :: Only
Classifier: License :: OSI Approved :: MIT License
Classifier: Typing :: Typed
Requires-Python: >=3.7
Requires-Dist: gym[atari,box2d,classic_control]
Requires-Dist: tensorflow-gpu
Provides-Extra: lint
Requires-Dist: prospector[with_everything] ; extra == 'lint'
Requires-Dist: mypy (==0.720) ; extra == 'lint'
Provides-Extra: mujoco
Requires-Dist: gym[mujoco,robotics] ; extra == 'mujoco'
Provides-Extra: test
Requires-Dist: tox ; extra == 'test'
